apccapi/__init__.py
apccapi/apccapi.py
apccapi-0.0.1.dist-info/LICENSE
apccapi-0.0.1.dist-info/METADATA
apccapi-0.0.1.dist-info/WHEEL
apccapi-0.0.1.dist-info/top_level.txt
apccapi-0.0.1.dist-info/RECORD
