Metadata-Version: 2.1
Name: apccapi
Version: 0.0.1
Summary: APCC Climate Information toolKit API package
Home-page: https://www.apcc21.org
Author: APEC Climate Center
Author-email: joohyung@apcc21.org
Project-URL: CLIK, https://cliks.apcc21.org
Keywords: APCC,apcc,Climate,Climate Information,Climate API
Classifier: Programming Language :: Python :: 3
Classifier: License :: OSI Approved :: MIT License
Classifier: Operating System :: OS Independent
Requires-Python: >=3.6
License-File: LICENSE
Requires-Dist: requests
Requires-Dist: urllib3
